ggist_cli_app/__init__.py
ggist_cli_app/__init__.pyc
ggist_cli_app/__main__.py
ggist_cli_app/consts.py
ggist_cli_app/settings.py
ggist_cli_app/__pycache__/__init__.cpython-39.pyc
ggist_cli_app/__pycache__/__main__.cpython-37.pyc
ggist_cli_app/__pycache__/__main__.cpython-39.pyc
ggist_cli_app/__pycache__/consts.cpython-37.pyc
ggist_cli_app/__pycache__/consts.cpython-39.pyc
ggist_cli_app/__pycache__/settings.cpython-37.pyc
ggist_cli_app/__pycache__/settings.cpython-39.pyc
ggist_cli_app/commands/__init__.py
ggist_cli_app/commands/groups.py
ggist_cli_app/commands/run.py
ggist_cli_app/commands/stubs.py
ggist_cli_app/commands/__pycache__/__init__.cpython-37.pyc
ggist_cli_app/commands/__pycache__/__init__.cpython-39.pyc
ggist_cli_app/commands/__pycache__/groups.cpython-39.pyc
ggist_cli_app/commands/__pycache__/run.cpython-37.pyc
ggist_cli_app/commands/__pycache__/run.cpython-39.pyc
ggist_cli_app/commands/__pycache__/stubs.cpython-39.pyc
ggist_cli_app/commands/subcommands/add.py
ggist_cli_app/commands/subcommands/remove.py
ggist_cli_app/commands/subcommands/show.py
ggist_cli_app/commands/subcommands/__pycache__/add.cpython-39.pyc
ggist_cli_app/commands/subcommands/__pycache__/remove.cpython-39.pyc
ggist_cli_app/commands/subcommands/__pycache__/show.cpython-39.pyc
ggist_cli_app/core/aliases.py
ggist_cli_app/core/os.py
ggist_cli_app/core/script_runner.py
ggist_cli_app/core/source.py
ggist_cli_app/core/sources_manager.py
ggist_cli_app/core/__pycache__/aliases.cpython-37.pyc
ggist_cli_app/core/__pycache__/aliases.cpython-39.pyc
ggist_cli_app/core/__pycache__/os.cpython-37.pyc
ggist_cli_app/core/__pycache__/os.cpython-39.pyc
ggist_cli_app/core/__pycache__/script_runner.cpython-37.pyc
ggist_cli_app/core/__pycache__/script_runner.cpython-39.pyc
ggist_cli_app/core/__pycache__/source.cpython-37.pyc
ggist_cli_app/core/__pycache__/source.cpython-39.pyc
ggist_cli_app/core/__pycache__/sources_manager.cpython-37.pyc
ggist_cli_app/core/__pycache__/sources_manager.cpython-39.pyc
ggist1-0.1.19.dist-info/LICENSE
ggist1-0.1.19.dist-info/METADATA
ggist1-0.1.19.dist-info/WHEEL
ggist1-0.1.19.dist-info/entry_points.txt
ggist1-0.1.19.dist-info/top_level.txt
ggist1-0.1.19.dist-info/RECORD
